<?xml version='1.0' encoding='utf-8'?>
<TextureAtlas imagePath="SurvivorBF.png">
<SubTexture name="BF_Down instance 0000" x="2274" y="2436" width="349" height="397" frameX="-36" frameY="-49" frameWidth="397" frameHeight="447" />
<SubTexture name="BF_Idle instance 0000" x="0" y="1105" width="314" height="468" frameX="-10" frameY="0" frameWidth="330" frameHeight="469" />
<SubTexture name="BF_Left instance 0000" x="0" y="2007" width="429" height="429" frameX="-5" frameY="-15" frameWidth="438" frameHeight="445" />
<SubTexture name="BF_Right instance 0000" x="1182" y="2007" width="330" height="425" frameX="-7" frameY="-15" frameWidth="359" frameHeight="441" />
<SubTexture name="BF_Spooked instance 0000" x="831" y="2007" width="351" height="429" frameX="-86" frameY="0" frameWidth="447" frameHeight="430" />
<SubTexture name="BF_Spooked instance 0001" x="1512" y="2007" width="439" height="424" frameX="-7" frameY="-5" frameWidth="447" frameHeight="430" />
<SubTexture name="BF_Spooked instance 0002" x="1951" y="2007" width="434" height="424" frameX="-13" frameY="-5" frameWidth="447" frameHeight="430" />
<SubTexture name="BF_Spooked instance 0003" x="2731" y="0" width="433" height="424" frameX="-14" frameY="-5" frameWidth="447" frameHeight="430" />
<SubTexture name="BF_Spooked instance 0004" x="2731" y="424" width="433" height="424" frameX="-13" frameY="-5" frameWidth="447" frameHeight="430" />
<SubTexture name="BF_Spooked instance 0005" x="2731" y="848" width="433" height="424" frameX="-13" frameY="-5" frameWidth="447" frameHeight="430" />
<SubTexture name="BF_Spooked instance 0006" x="0" y="2436" width="434" height="424" frameX="-13" frameY="-5" frameWidth="447" frameHeight="430" />
<SubTexture name="BF_Spooked instance 0007" x="0" y="2436" width="434" height="424" frameX="-13" frameY="-5" frameWidth="447" frameHeight="430" />
<SubTexture name="BF_Spooked instance 0008" x="0" y="2436" width="434" height="424" frameX="-13" frameY="-5" frameWidth="447" frameHeight="430" />
<SubTexture name="BF_Spooked instance 0009" x="0" y="2436" width="434" height="424" frameX="-13" frameY="-5" frameWidth="447" frameHeight="430" />
<SubTexture name="BF_Spooked instance 0010" x="0" y="2436" width="434" height="424" frameX="-13" frameY="-5" frameWidth="447" frameHeight="430" />
<SubTexture name="BF_Spooked instance 0011" x="0" y="2436" width="434" height="424" frameX="-13" frameY="-5" frameWidth="447" frameHeight="430" />
<SubTexture name="BF_Spooked instance 0012" x="0" y="2436" width="434" height="424" frameX="-13" frameY="-5" frameWidth="447" frameHeight="430" />
<SubTexture name="BF_Spooked instance 0013" x="0" y="2436" width="434" height="424" frameX="-13" frameY="-5" frameWidth="447" frameHeight="430" />
<SubTexture name="BF_Spooked instance 0014" x="0" y="2436" width="434" height="424" frameX="-13" frameY="-5" frameWidth="447" frameHeight="430" />
<SubTexture name="BF_Spooked instance 0015" x="0" y="2436" width="434" height="424" frameX="-13" frameY="-5" frameWidth="447" frameHeight="430" />
<SubTexture name="BF_Spooked instance 0016" x="0" y="2436" width="434" height="424" frameX="-13" frameY="-5" frameWidth="447" frameHeight="430" />
<SubTexture name="BF_Spooked instance 0017" x="0" y="2436" width="434" height="424" frameX="-13" frameY="-5" frameWidth="447" frameHeight="430" />
<SubTexture name="BF_Spooked instance 0018" x="0" y="2436" width="434" height="424" frameX="-13" frameY="-5" frameWidth="447" frameHeight="430" />
<SubTexture name="BF_Spooked instance 0019" x="0" y="2436" width="434" height="424" frameX="-13" frameY="-5" frameWidth="447" frameHeight="430" />
<SubTexture name="BF_Spooked instance 0020" x="0" y="2436" width="434" height="424" frameX="-13" frameY="-5" frameWidth="447" frameHeight="430" />
<SubTexture name="BF_Spooked instance 0021" x="0" y="2436" width="434" height="424" frameX="-13" frameY="-5" frameWidth="447" frameHeight="430" />
<SubTexture name="BF_Spooked instance 0022" x="0" y="2436" width="434" height="424" frameX="-13" frameY="-5" frameWidth="447" frameHeight="430" />
<SubTexture name="BF_Spooked instance 0023" x="0" y="2436" width="434" height="424" frameX="-13" frameY="-5" frameWidth="447" frameHeight="430" />
<SubTexture name="BF_Spooked instance 0024" x="0" y="2436" width="434" height="424" frameX="-13" frameY="-5" frameWidth="447" frameHeight="430" />
<SubTexture name="BF_Spooked instance 0025" x="0" y="2436" width="434" height="424" frameX="-13" frameY="-5" frameWidth="447" frameHeight="430" />
<SubTexture name="BF_Spooked instance 0026" x="0" y="2436" width="434" height="424" frameX="-13" frameY="-5" frameWidth="447" frameHeight="430" />
<SubTexture name="BF_Spooked instance 0027" x="0" y="2436" width="434" height="424" frameX="-13" frameY="-5" frameWidth="447" frameHeight="430" />
<SubTexture name="BF_Spooked instance 0028" x="0" y="2436" width="434" height="424" frameX="-13" frameY="-5" frameWidth="447" frameHeight="430" />
<SubTexture name="BF_Spooked instance 0029" x="0" y="2436" width="434" height="424" frameX="-13" frameY="-5" frameWidth="447" frameHeight="430" />
<SubTexture name="BF_Spooked instance 0030" x="0" y="2436" width="434" height="424" frameX="-13" frameY="-5" frameWidth="447" frameHeight="430" />
<SubTexture name="BF_Spooked instance 0031" x="0" y="2436" width="434" height="424" frameX="-13" frameY="-5" frameWidth="447" frameHeight="430" />
<SubTexture name="BF_Spooked instance 0032" x="0" y="2436" width="434" height="424" frameX="-13" frameY="-5" frameWidth="447" frameHeight="430" />
<SubTexture name="BF_Spooked instance 0033" x="0" y="2436" width="434" height="424" frameX="-13" frameY="-5" frameWidth="447" frameHeight="430" />
<SubTexture name="BF_Spooked instance 0034" x="0" y="2436" width="434" height="424" frameX="-13" frameY="-5" frameWidth="447" frameHeight="430" />
<SubTexture name="BF_Spooked instance 0035" x="0" y="2436" width="434" height="424" frameX="-13" frameY="-5" frameWidth="447" frameHeight="430" />
<SubTexture name="BF_Spooked instance 0036" x="0" y="2436" width="434" height="424" frameX="-13" frameY="-5" frameWidth="447" frameHeight="430" />
<SubTexture name="BF_Spooked instance 0037" x="0" y="2436" width="434" height="424" frameX="-13" frameY="-5" frameWidth="447" frameHeight="430" />
<SubTexture name="BF_Spooked instance 0038" x="0" y="2436" width="434" height="424" frameX="-13" frameY="-5" frameWidth="447" frameHeight="430" />
<SubTexture name="BF_Spooked instance 0039" x="0" y="2436" width="434" height="424" frameX="-13" frameY="-5" frameWidth="447" frameHeight="430" />
<SubTexture name="BF_Spooked instance 0040" x="0" y="2436" width="434" height="424" frameX="-13" frameY="-5" frameWidth="447" frameHeight="430" />
<SubTexture name="BF_Spooked instance 0041" x="0" y="2436" width="434" height="424" frameX="-13" frameY="-5" frameWidth="447" frameHeight="430" />
<SubTexture name="BF_Spooked instance 0042" x="0" y="2436" width="434" height="424" frameX="-13" frameY="-5" frameWidth="447" frameHeight="430" />
<SubTexture name="BF_Spooked instance 0043" x="0" y="2436" width="434" height="424" frameX="-13" frameY="-5" frameWidth="447" frameHeight="430" />
<SubTexture name="BF_Spooked instance 0044" x="0" y="2436" width="434" height="424" frameX="-13" frameY="-5" frameWidth="447" frameHeight="430" />
<SubTexture name="BF_Spooked instance 0045" x="0" y="2436" width="434" height="424" frameX="-13" frameY="-5" frameWidth="447" frameHeight="430" />
<SubTexture name="BF_Spooked instance 0046" x="0" y="2436" width="434" height="424" frameX="-13" frameY="-5" frameWidth="447" frameHeight="430" />
<SubTexture name="BF_Spooked instance 0047" x="0" y="2436" width="434" height="424" frameX="-13" frameY="-5" frameWidth="447" frameHeight="430" />
<SubTexture name="BF_Spooked instance 0048" x="0" y="2436" width="434" height="424" frameX="-13" frameY="-5" frameWidth="447" frameHeight="430" />
<SubTexture name="BF_Spooked instance 0049" x="0" y="2436" width="434" height="424" frameX="-13" frameY="-5" frameWidth="447" frameHeight="430" />
<SubTexture name="BF_Spooked instance 0050" x="0" y="2436" width="434" height="424" frameX="-13" frameY="-5" frameWidth="447" frameHeight="430" />
<SubTexture name="BF_Spooked instance 0051" x="0" y="2436" width="434" height="424" frameX="-13" frameY="-5" frameWidth="447" frameHeight="430" />
<SubTexture name="BF_Spooked instance 0052" x="0" y="2436" width="434" height="424" frameX="-13" frameY="-5" frameWidth="447" frameHeight="430" />
<SubTexture name="BF_Spooked instance 0053" x="0" y="2436" width="434" height="424" frameX="-13" frameY="-5" frameWidth="447" frameHeight="430" />
<SubTexture name="BF_Spooked instance 0054" x="0" y="2436" width="434" height="424" frameX="-13" frameY="-5" frameWidth="447" frameHeight="430" />
<SubTexture name="BF_Spooked instance 0055" x="0" y="2436" width="434" height="424" frameX="-13" frameY="-5" frameWidth="447" frameHeight="430" />
<SubTexture name="BF_Spooked instance 0056" x="0" y="2436" width="434" height="424" frameX="-13" frameY="-5" frameWidth="447" frameHeight="430" />
<SubTexture name="BF_Spooked instance 0057" x="0" y="2436" width="434" height="424" frameX="-13" frameY="-5" frameWidth="447" frameHeight="430" />
<SubTexture name="BF_Spooked instance 0058" x="0" y="2436" width="434" height="424" frameX="-13" frameY="-5" frameWidth="447" frameHeight="430" />
<SubTexture name="BF_Spooked instance 0059" x="0" y="2436" width="434" height="424" frameX="-13" frameY="-5" frameWidth="447" frameHeight="430" />
<SubTexture name="BF_Spooked instance 0060" x="0" y="2436" width="434" height="424" frameX="-13" frameY="-5" frameWidth="447" frameHeight="430" />
<SubTexture name="BF_Spooked instance 0061" x="0" y="2436" width="434" height="424" frameX="-13" frameY="-5" frameWidth="447" frameHeight="430" />
<SubTexture name="BF_Spooked instance 0062" x="0" y="2436" width="434" height="424" frameX="-13" frameY="-5" frameWidth="447" frameHeight="430" />
<SubTexture name="BF_Spooked instance 0063" x="0" y="2436" width="434" height="424" frameX="-13" frameY="-5" frameWidth="447" frameHeight="430" />
<SubTexture name="BF_Spooked instance 0064" x="0" y="2436" width="434" height="424" frameX="-13" frameY="-5" frameWidth="447" frameHeight="430" />
<SubTexture name="BF_Spooked instance 0065" x="0" y="2436" width="434" height="424" frameX="-13" frameY="-5" frameWidth="447" frameHeight="430" />
<SubTexture name="BF_Spooked instance 0066" x="0" y="2436" width="434" height="424" frameX="-13" frameY="-5" frameWidth="447" frameHeight="430" />
<SubTexture name="BF_Spooked instance 0067" x="0" y="2436" width="434" height="424" frameX="-13" frameY="-5" frameWidth="447" frameHeight="430" />
<SubTexture name="BF_Spooked instance 0068" x="0" y="2436" width="434" height="424" frameX="-13" frameY="-5" frameWidth="447" frameHeight="430" />
<SubTexture name="BF_Spooked instance 0069" x="0" y="2436" width="434" height="424" frameX="-13" frameY="-5" frameWidth="447" frameHeight="430" />
<SubTexture name="BF_Spooked instance 0070" x="0" y="2436" width="434" height="424" frameX="-13" frameY="-5" frameWidth="447" frameHeight="430" />
<SubTexture name="BF_Spooked instance 0071" x="0" y="2436" width="434" height="424" frameX="-13" frameY="-5" frameWidth="447" frameHeight="430" />
<SubTexture name="BF_Spooked instance 0072" x="0" y="2436" width="434" height="424" frameX="-13" frameY="-5" frameWidth="447" frameHeight="430" />
<SubTexture name="BF_Spooked instance 0073" x="0" y="2436" width="434" height="424" frameX="-13" frameY="-5" frameWidth="447" frameHeight="430" />
<SubTexture name="BF_Spooked instance 0074" x="0" y="2436" width="434" height="424" frameX="-13" frameY="-5" frameWidth="447" frameHeight="430" />
<SubTexture name="BF_Spooked instance 0075" x="0" y="2436" width="434" height="424" frameX="-13" frameY="-5" frameWidth="447" frameHeight="430" />
<SubTexture name="BF_Spooked instance 0076" x="0" y="2436" width="434" height="424" frameX="-13" frameY="-5" frameWidth="447" frameHeight="430" />
<SubTexture name="BF_Spooked instance 0077" x="0" y="2436" width="434" height="424" frameX="-13" frameY="-5" frameWidth="447" frameHeight="430" />
<SubTexture name="BF_Spooked instance 0078" x="0" y="2436" width="434" height="424" frameX="-13" frameY="-5" frameWidth="447" frameHeight="430" />
<SubTexture name="BF_Spooked instance 0079" x="0" y="2436" width="434" height="424" frameX="-13" frameY="-5" frameWidth="447" frameHeight="430" />
<SubTexture name="BF_Spooked instance 0080" x="0" y="2436" width="434" height="424" frameX="-13" frameY="-5" frameWidth="447" frameHeight="430" />
<SubTexture name="BF_Spooked instance 0081" x="0" y="2436" width="434" height="424" frameX="-13" frameY="-5" frameWidth="447" frameHeight="430" />
<SubTexture name="BF_Spooked instance 0082" x="0" y="2436" width="434" height="424" frameX="-13" frameY="-5" frameWidth="447" frameHeight="430" />
<SubTexture name="BF_Up instance 0000" x="0" y="0" width="301" height="584" frameX="-23" frameY="0" frameWidth="347" frameHeight="584" />
</TextureAtlas>
